cryptionpy/__init__.py
cryptionpy/cli.py
cryptionpy/encryption.py
cryptionpy-1.0.0.dist-info/LICENSE
cryptionpy-1.0.0.dist-info/METADATA
cryptionpy-1.0.0.dist-info/WHEEL
cryptionpy-1.0.0.dist-info/entry_points.txt
cryptionpy-1.0.0.dist-info/top_level.txt
cryptionpy-1.0.0.dist-info/RECORD
