Metadata-Version: 2.1
Name: cryptionpy
Version: 1.0.0
Summary: A package for encrypting and decrypting Python files using base64 or emoji obfuscation.
Home-page: https://github.com/ByteBreach/cryptionpy
Author: MrFidal
Author-email: mrfidal@proton.me
Classifier: Programming Language :: Python :: 3
Classifier: License :: OSI Approved :: MIT License
Classifier: Operating System :: OS Independent
Requires-Python: >=3.6
License-File: LICENSE
